grimlock/__init__.py
grimlock/convenience.py
grimlock-0.0.1.dist-info/METADATA
grimlock-0.0.1.dist-info/RECORD
grimlock-0.0.1.dist-info/WHEEL
grimlock-0.0.1.dist-info/top_level.txt
