Metadata-Version: 2.1
Name: grimlock
Version: 0.0.1
Summary: Simple tool that assists with preprocessing pandas dataframes for Machine Learning.
Home-page: https://github.com/BellwethrInc/grimlock
Author: Matt Moody
Author-email: matt@bellwethr.com
License: UNKNOWN
Platform: UNKNOWN
Classifier: Programming Language :: Python :: 3
Classifier: License :: OSI Approved :: MIT License
Classifier: Operating System :: OS Independent
Requires-Dist: numpy
Requires-Dist: pandas
